MANIFEST.in
README.md
ctznosx.conf
ctznosx.db
requirements.txt
setup.py
ctznosx/__init__.py
ctznosx/cli.py
ctznosx/config.py
ctznosx/devicemgmt.py
ctznosx/exceptions.py
ctznosx/launcher.py
ctznosx/monitors.py
ctznosx/report.py
ctznosx/usage.py
ctznosx/watcher.py
ctznosx.egg-info/PKG-INFO
ctznosx.egg-info/SOURCES.txt
ctznosx.egg-info/dependency_links.txt
ctznosx.egg-info/requires.txt
ctznosx.egg-info/top_level.txt
monitors/README.md
plist/com.ctznosx.dir.watcher.plist
plist/com.ctznosx.runner.plist
plist/com.ctznosx.watcher.plist
plist/com.ctznosx.wifi.watcher.plist
scripts/ctznosx
scripts/ctznosx-watcher